[
    {
        "Category": "January",
        "Value": 205816
    },
    {
        "Category": "February",
        "Value": 444140
    },
    {
        "Category": "July",
        "Value": 32868
    },
    {
        "Category": "August",
        "Value": 100957
    },
    {
        "Category": "September",
        "Value": 79883
    },
    {
        "Category": "October",
        "Value": 23874
    },
    {
        "Category": "November",
        "Value": 64524
    },
    {
        "Category": "December",
        "Value": 195192
    }
]